{
  "contentTypes": [
    {
      "sys": {
        "space": {
          "sys": {
            "type": "Link",
            "linkType": "Space",
            "id": "9y6bw8wj9521"
          }
        },
        "id": "workExperience",
        "type": "ContentType",
        "createdAt": "2024-04-18T05:16:20.204Z",
        "updatedAt": "2024-04-24T02:11:25.275Z",
        "environment": {
          "sys": {
            "id": "master",
            "type": "Link",
            "linkType": "Environment"
          }
        },
        "publishedVersion": 5,
        "publishedAt": "2024-04-24T02:11:25.275Z",
        "firstPublishedAt": "2024-04-18T05:16:20.724Z",
        "createdBy": {
          "sys": {
            "type": "Link",
            "linkType": "User",
            "id": "24xELcGAn6cqGiuyQLS1MD"
          }
        },
        "updatedBy": {
          "sys": {
            "type": "Link",
            "linkType": "User",
            "id": "24xELcGAn6cqGiuyQLS1MD"
          }
        },
        "publishedCounter": 3,
        "version": 6,
        "publishedBy": {
          "sys": {
            "type": "Link",
            "linkType": "User",
            "id": "24xELcGAn6cqGiuyQLS1MD"
          }
        },
        "urn": "crn:contentful:::content:spaces/9y6bw8wj9521/environments/master/content_types/workExperience"
      },
      "displayField": "title",
      "name": "Work Experience",
      "description": "An entry for a work experience",
      "fields": [
        {
          "id": "title",
          "name": "Title",
          "type": "Symbol",
          "localized": false,
          "required": true,
          "validations": [
            {
              "unique": true
            }
          ],
          "disabled": false,
          "omitted": false
        },
        {
          "id": "position",
          "name": "Position",
          "type": "Symbol",
          "localized": false,
          "required": true,
          "validations": [
          ],
          "disabled": false,
          "omitted": false
        },
        {
          "id": "slug",
          "name": "Slug",
          "type": "Symbol",
          "localized": false,
          "required": true,
          "validations": [
            {
              "unique": true
            }
          ],
          "disabled": false,
          "omitted": false
        },
        {
          "id": "description",
          "name": "Description",
          "type": "RichText",
          "localized": false,
          "required": false,
          "validations": [
            {
              "enabledMarks": [
                "bold",
                "italic",
                "underline",
                "code",
                "superscript",
                "subscript"
              ],
              "message": "Only bold, italic, underline, code, superscript, and subscript marks are allowed"
            },
            {
              "enabledNodeTypes": [
                "heading-1",
                "heading-2",
                "heading-3",
                "heading-4",
                "heading-5",
                "heading-6",
                "ordered-list",
                "unordered-list",
                "hr",
                "blockquote",
                "embedded-entry-block",
                "embedded-asset-block",
                "table",
                "hyperlink",
                "entry-hyperlink",
                "asset-hyperlink",
                "embedded-entry-inline"
              ],
              "message": "Only heading 1, heading 2, heading 3, heading 4, heading 5, heading 6, ordered list, unordered list, horizontal rule, quote, block entry, asset, table, link to Url, link to entry, link to asset, and inline entry nodes are allowed"
            },
            {
              "nodes": {
              }
            }
          ],
          "disabled": false,
          "omitted": false
        },
        {
          "id": "workDateRange",
          "name": "Work Date Range",
          "type": "Symbol",
          "localized": false,
          "required": true,
          "validations": [
          ],
          "disabled": false,
          "omitted": false
        },
        {
          "id": "companyLogo",
          "name": "Company Logo",
          "type": "Link",
          "localized": false,
          "required": false,
          "validations": [
          ],
          "disabled": false,
          "omitted": false,
          "linkType": "Asset"
        },
        {
          "id": "workGallery",
          "name": "Work Gallery",
          "type": "Array",
          "localized": false,
          "required": false,
          "validations": [
          ],
          "disabled": false,
          "omitted": false,
          "items": {
            "type": "Link",
            "validations": [
            ],
            "linkType": "Asset"
          }
        }
      ]
    },
    {
      "sys": {
        "space": {
          "sys": {
            "type": "Link",
            "linkType": "Space",
            "id": "9y6bw8wj9521"
          }
        },
        "id": "workPage",
        "type": "ContentType",
        "createdAt": "2024-04-18T05:19:42.084Z",
        "updatedAt": "2024-04-24T02:12:33.451Z",
        "environment": {
          "sys": {
            "id": "master",
            "type": "Link",
            "linkType": "Environment"
          }
        },
        "publishedVersion": 15,
        "publishedAt": "2024-04-24T02:12:33.451Z",
        "firstPublishedAt": "2024-04-18T05:19:42.709Z",
        "createdBy": {
          "sys": {
            "type": "Link",
            "linkType": "User",
            "id": "24xELcGAn6cqGiuyQLS1MD"
          }
        },
        "updatedBy": {
          "sys": {
            "type": "Link",
            "linkType": "User",
            "id": "24xELcGAn6cqGiuyQLS1MD"
          }
        },
        "publishedCounter": 8,
        "version": 16,
        "publishedBy": {
          "sys": {
            "type": "Link",
            "linkType": "User",
            "id": "24xELcGAn6cqGiuyQLS1MD"
          }
        },
        "urn": "crn:contentful:::content:spaces/9y6bw8wj9521/environments/master/content_types/workPage"
      },
      "displayField": "pageTitle",
      "name": "Work Page",
      "description": "Contents for work page",
      "fields": [
        {
          "id": "pageTitle",
          "name": "Page Title",
          "type": "Symbol",
          "localized": false,
          "required": true,
          "validations": [
          ],
          "disabled": false,
          "omitted": false
        },
        {
          "id": "workHero",
          "name": "Work Hero",
          "type": "Link",
          "localized": false,
          "required": true,
          "validations": [
            {
              "linkContentType": [
                "hero"
              ]
            }
          ],
          "disabled": false,
          "omitted": false,
          "linkType": "Entry"
        },
        {
          "id": "workExperiences",
          "name": "Work Experiences",
          "type": "Array",
          "localized": false,
          "required": false,
          "validations": [
          ],
          "disabled": false,
          "omitted": false,
          "items": {
            "type": "Link",
            "validations": [
              {
                "linkContentType": [
                  "workExperience"
                ]
              }
            ],
            "linkType": "Entry"
          }
        }
      ]
    },
    {
      "sys": {
        "space": {
          "sys": {
            "type": "Link",
            "linkType": "Space",
            "id": "9y6bw8wj9521"
          }
        },
        "id": "hero",
        "type": "ContentType",
        "createdAt": "2024-04-24T01:31:52.079Z",
        "updatedAt": "2024-04-24T02:12:18.991Z",
        "environment": {
          "sys": {
            "id": "master",
            "type": "Link",
            "linkType": "Environment"
          }
        },
        "publishedVersion": 3,
        "publishedAt": "2024-04-24T02:12:18.991Z",
        "firstPublishedAt": "2024-04-24T01:31:52.538Z",
        "createdBy": {
          "sys": {
            "type": "Link",
            "linkType": "User",
            "id": "24xELcGAn6cqGiuyQLS1MD"
          }
        },
        "updatedBy": {
          "sys": {
            "type": "Link",
            "linkType": "User",
            "id": "24xELcGAn6cqGiuyQLS1MD"
          }
        },
        "publishedCounter": 2,
        "version": 4,
        "publishedBy": {
          "sys": {
            "type": "Link",
            "linkType": "User",
            "id": "24xELcGAn6cqGiuyQLS1MD"
          }
        },
        "urn": "crn:contentful:::content:spaces/9y6bw8wj9521/environments/master/content_types/hero"
      },
      "displayField": "heroTitle",
      "name": "Hero",
      "description": "Hero component with title, body, and image",
      "fields": [
        {
          "id": "heroTitle",
          "name": "Hero Title",
          "type": "Symbol",
          "localized": false,
          "required": true,
          "validations": [
          ],
          "disabled": false,
          "omitted": false
        },
        {
          "id": "heroBody",
          "name": "Hero Body",
          "type": "Text",
          "localized": false,
          "required": false,
          "validations": [
          ],
          "disabled": false,
          "omitted": false
        },
        {
          "id": "heroImage",
          "name": "Hero Image",
          "type": "Link",
          "localized": false,
          "required": false,
          "validations": [
          ],
          "disabled": false,
          "omitted": false,
          "linkType": "Asset"
        }
      ]
    }
  ],
  "tags": [
  ],
  "editorInterfaces": [
    {
      "sys": {
        "id": "default",
        "type": "EditorInterface",
        "space": {
          "sys": {
            "id": "9y6bw8wj9521",
            "type": "Link",
            "linkType": "Space"
          }
        },
        "version": 6,
        "createdAt": "2024-04-18T05:16:20.899Z",
        "createdBy": {
          "sys": {
            "id": "24xELcGAn6cqGiuyQLS1MD",
            "type": "Link",
            "linkType": "User"
          }
        },
        "updatedAt": "2024-04-24T02:11:26.242Z",
        "updatedBy": {
          "sys": {
            "id": "24xELcGAn6cqGiuyQLS1MD",
            "type": "Link",
            "linkType": "User"
          }
        },
        "contentType": {
          "sys": {
            "id": "workExperience",
            "type": "Link",
            "linkType": "ContentType"
          }
        },
        "environment": {
          "sys": {
            "id": "master",
            "type": "Link",
            "linkType": "Environment"
          }
        }
      },
      "controls": [
        {
          "fieldId": "title",
          "widgetId": "singleLine",
          "widgetNamespace": "builtin"
        },
        {
          "fieldId": "position",
          "widgetId": "singleLine",
          "widgetNamespace": "builtin"
        },
        {
          "fieldId": "slug",
          "settings": {
            "trackingFieldId": "title"
          },
          "widgetId": "slugEditor",
          "widgetNamespace": "builtin"
        },
        {
          "fieldId": "description",
          "widgetId": "richTextEditor",
          "widgetNamespace": "builtin"
        },
        {
          "fieldId": "workDateRange",
          "widgetId": "singleLine",
          "widgetNamespace": "builtin"
        },
        {
          "fieldId": "companyLogo",
          "widgetId": "assetLinkEditor",
          "widgetNamespace": "builtin"
        },
        {
          "fieldId": "workGallery",
          "widgetId": "assetGalleryEditor",
          "widgetNamespace": "builtin"
        }
      ]
    },
    {
      "sys": {
        "id": "default",
        "type": "EditorInterface",
        "space": {
          "sys": {
            "id": "9y6bw8wj9521",
            "type": "Link",
            "linkType": "Space"
          }
        },
        "version": 16,
        "createdAt": "2024-04-18T05:19:42.898Z",
        "createdBy": {
          "sys": {
            "id": "24xELcGAn6cqGiuyQLS1MD",
            "type": "Link",
            "linkType": "User"
          }
        },
        "updatedAt": "2024-04-24T02:12:34.305Z",
        "updatedBy": {
          "sys": {
            "id": "24xELcGAn6cqGiuyQLS1MD",
            "type": "Link",
            "linkType": "User"
          }
        },
        "contentType": {
          "sys": {
            "id": "workPage",
            "type": "Link",
            "linkType": "ContentType"
          }
        },
        "environment": {
          "sys": {
            "id": "master",
            "type": "Link",
            "linkType": "Environment"
          }
        }
      },
      "controls": [
        {
          "fieldId": "pageTitle",
          "widgetId": "singleLine",
          "widgetNamespace": "builtin"
        },
        {
          "fieldId": "workHero",
          "widgetId": "entryLinkEditor",
          "widgetNamespace": "builtin"
        },
        {
          "fieldId": "workExperiences",
          "widgetId": "entryCardsEditor",
          "widgetNamespace": "builtin"
        }
      ]
    },
    {
      "sys": {
        "id": "default",
        "type": "EditorInterface",
        "space": {
          "sys": {
            "id": "9y6bw8wj9521",
            "type": "Link",
            "linkType": "Space"
          }
        },
        "version": 4,
        "createdAt": "2024-04-24T01:31:52.695Z",
        "createdBy": {
          "sys": {
            "id": "24xELcGAn6cqGiuyQLS1MD",
            "type": "Link",
            "linkType": "User"
          }
        },
        "updatedAt": "2024-04-24T02:12:20.050Z",
        "updatedBy": {
          "sys": {
            "id": "24xELcGAn6cqGiuyQLS1MD",
            "type": "Link",
            "linkType": "User"
          }
        },
        "contentType": {
          "sys": {
            "id": "hero",
            "type": "Link",
            "linkType": "ContentType"
          }
        },
        "environment": {
          "sys": {
            "id": "master",
            "type": "Link",
            "linkType": "Environment"
          }
        }
      },
      "controls": [
        {
          "fieldId": "heroTitle",
          "widgetId": "singleLine",
          "widgetNamespace": "builtin"
        },
        {
          "fieldId": "heroBody",
          "widgetId": "markdown",
          "widgetNamespace": "builtin"
        },
        {
          "fieldId": "heroImage",
          "widgetId": "assetLinkEditor",
          "widgetNamespace": "builtin"
        }
      ]
    }
  ],
  "entries": [
    {
      "metadata": {
        "tags": [
        ]
      },
      "sys": {
        "space": {
          "sys": {
            "type": "Link",
            "linkType": "Space",
            "id": "9y6bw8wj9521"
          }
        },
        "id": "3UcGDWqEXwSMbDmcv95f42",
        "type": "Entry",
        "createdAt": "2024-04-18T07:00:58.339Z",
        "updatedAt": "2024-04-18T07:05:24.717Z",
        "environment": {
          "sys": {
            "id": "master",
            "type": "Link",
            "linkType": "Environment"
          }
        },
        "publishedVersion": 10,
        "publishedAt": "2024-04-18T07:05:24.717Z",
        "firstPublishedAt": "2024-04-18T07:04:35.691Z",
        "createdBy": {
          "sys": {
            "type": "Link",
            "linkType": "User",
            "id": "24xELcGAn6cqGiuyQLS1MD"
          }
        },
        "updatedBy": {
          "sys": {
            "type": "Link",
            "linkType": "User",
            "id": "24xELcGAn6cqGiuyQLS1MD"
          }
        },
        "publishedCounter": 2,
        "version": 11,
        "publishedBy": {
          "sys": {
            "type": "Link",
            "linkType": "User",
            "id": "24xELcGAn6cqGiuyQLS1MD"
          }
        },
        "automationTags": [
        ],
        "contentType": {
          "sys": {
            "type": "Link",
            "linkType": "ContentType",
            "id": "workExperience"
          }
        },
        "urn": "crn:contentful:::content:spaces/9y6bw8wj9521/environments/master/entries/3UcGDWqEXwSMbDmcv95f42"
      },
      "fields": {
        "title": {
          "en-US": "Fujitsu Philippines"
        },
        "position": {
          "en-US": "Application Systems Engineer"
        },
        "slug": {
          "en-US": "fujitsu-philippines"
        },
        "description": {
          "en-US": {
            "data": {
            },
            "content": [
              {
                "data": {
                },
                "content": [
                  {
                    "data": {
                    },
                    "marks": [
                    ],
                    "value": "My first full time job. Created applications for banking systems in Japan. Made prototypes for demos and converting prospects into clients.",
                    "nodeType": "text"
                  }
                ],
                "nodeType": "paragraph"
              },
              {
                "data": {
                },
                "content": [
                  {
                    "data": {
                    },
                    "marks": [
                    ],
                    "value": "Everything that I have experienced here shaped me to who I am today. I have learned a lot not only the technologies I used, but also the values in life that I am carrying with me up until this point. I have also made some of my closest friends here. They helped and supported me throughout my career in Fujitsu. Our teamwork made difficult work easy and fun.",
                    "nodeType": "text"
                  }
                ],
                "nodeType": "paragraph"
              }
            ],
            "nodeType": "document"
          }
        },
        "workDateRange": {
          "en-US": "October 2016 - February 2020"
        },
        "companyLogo": {
          "en-US": {
            "sys": {
              "type": "Link",
              "linkType": "Asset",
              "id": "18fcwON5KIn0vA8D36m85i"
            }
          }
        }
      }
    },
    {
      "metadata": {
        "tags": [
        ]
      },
      "sys": {
        "space": {
          "sys": {
            "type": "Link",
            "linkType": "Space",
            "id": "9y6bw8wj9521"
          }
        },
        "id": "2VwWUw2OuCu3klok0xzk78",
        "type": "Entry",
        "createdAt": "2024-04-18T07:05:33.886Z",
        "updatedAt": "2024-04-18T07:07:30.368Z",
        "environment": {
          "sys": {
            "id": "master",
            "type": "Link",
            "linkType": "Environment"
          }
        },
        "publishedVersion": 10,
        "publishedAt": "2024-04-18T07:07:30.368Z",
        "firstPublishedAt": "2024-04-18T07:07:30.368Z",
        "createdBy": {
          "sys": {
            "type": "Link",
            "linkType": "User",
            "id": "24xELcGAn6cqGiuyQLS1MD"
          }
        },
        "updatedBy": {
          "sys": {
            "type": "Link",
            "linkType": "User",
            "id": "24xELcGAn6cqGiuyQLS1MD"
          }
        },
        "publishedCounter": 1,
        "version": 11,
        "publishedBy": {
          "sys": {
            "type": "Link",
            "linkType": "User",
            "id": "24xELcGAn6cqGiuyQLS1MD"
          }
        },
        "automationTags": [
        ],
        "contentType": {
          "sys": {
            "type": "Link",
            "linkType": "ContentType",
            "id": "workExperience"
          }
        },
        "urn": "crn:contentful:::content:spaces/9y6bw8wj9521/environments/master/entries/2VwWUw2OuCu3klok0xzk78"
      },
      "fields": {
        "title": {
          "en-US": "Tanda | Workforce.com"
        },
        "position": {
          "en-US": "Frontend Web Developer"
        },
        "slug": {
          "en-US": "tanda-workforce-com"
        },
        "description": {
          "en-US": {
            "data": {
            },
            "content": [
              {
                "data": {
                },
                "content": [
                  {
                    "data": {
                    },
                    "marks": [
                    ],
                    "value": "Became part of Tanda's marketing team. I created pages on the marketing website and helped on transitioning to their new brand, Workforce. Met people on different fields such as marketing manager, designers, content creators, and SEO specialists.",
                    "nodeType": "text"
                  }
                ],
                "nodeType": "paragraph"
              },
              {
                "data": {
                },
                "content": [
                  {
                    "data": {
                    },
                    "marks": [
                    ],
                    "value": "I've met some of the most fun and talented people here in Tanda and I wish I could have worked with them longer. Because of the COVID-19 pandemic, Tanda had to lay off some of their employees. I have experienced a lot of new and challenging things and despite of what happened, I'm still thankful because it made me wiser and stronger.",
                    "nodeType": "text"
                  }
                ],
                "nodeType": "paragraph"
              }
            ],
            "nodeType": "document"
          }
        },
        "workDateRange": {
          "en-US": "February 2020 - April 2020"
        },
        "companyLogo": {
          "en-US": {
            "sys": {
              "type": "Link",
              "linkType": "Asset",
              "id": "4Pl0qxQ4LYY32mhC9WH8Qr"
            }
          }
        }
      }
    },
    {
      "metadata": {
        "tags": [
        ]
      },
      "sys": {
        "space": {
          "sys": {
            "type": "Link",
            "linkType": "Space",
            "id": "9y6bw8wj9521"
          }
        },
        "id": "2Rgw7jRNbtVeLGDZMFSdd5",
        "type": "Entry",
        "createdAt": "2024-04-18T07:07:50.649Z",
        "updatedAt": "2024-04-24T02:14:32.725Z",
        "environment": {
          "sys": {
            "id": "master",
            "type": "Link",
            "linkType": "Environment"
          }
        },
        "publishedVersion": 18,
        "publishedAt": "2024-04-24T02:14:32.725Z",
        "firstPublishedAt": "2024-04-18T07:09:04.960Z",
        "createdBy": {
          "sys": {
            "type": "Link",
            "linkType": "User",
            "id": "24xELcGAn6cqGiuyQLS1MD"
          }
        },
        "updatedBy": {
          "sys": {
            "type": "Link",
            "linkType": "User",
            "id": "24xELcGAn6cqGiuyQLS1MD"
          }
        },
        "publishedCounter": 4,
        "version": 19,
        "publishedBy": {
          "sys": {
            "type": "Link",
            "linkType": "User",
            "id": "24xELcGAn6cqGiuyQLS1MD"
          }
        },
        "automationTags": [
        ],
        "contentType": {
          "sys": {
            "type": "Link",
            "linkType": "ContentType",
            "id": "workPage"
          }
        },
        "urn": "crn:contentful:::content:spaces/9y6bw8wj9521/environments/master/entries/2Rgw7jRNbtVeLGDZMFSdd5"
      },
      "fields": {
        "pageTitle": {
          "en-US": "Work Page"
        },
        "workHero": {
          "en-US": {
            "sys": {
              "type": "Link",
              "linkType": "Entry",
              "id": "2RVp0aUqSs3oQYkM1T3Yv2"
            }
          }
        },
        "workExperiences": {
          "en-US": [
            {
              "sys": {
                "type": "Link",
                "linkType": "Entry",
                "id": "3UcGDWqEXwSMbDmcv95f42"
              }
            },
            {
              "sys": {
                "type": "Link",
                "linkType": "Entry",
                "id": "2VwWUw2OuCu3klok0xzk78"
              }
            }
          ]
        }
      }
    },
    {
      "metadata": {
        "tags": [
        ]
      },
      "sys": {
        "space": {
          "sys": {
            "type": "Link",
            "linkType": "Space",
            "id": "9y6bw8wj9521"
          }
        },
        "id": "2RVp0aUqSs3oQYkM1T3Yv2",
        "type": "Entry",
        "createdAt": "2024-04-24T02:06:49.153Z",
        "updatedAt": "2024-04-24T02:09:35.404Z",
        "environment": {
          "sys": {
            "id": "master",
            "type": "Link",
            "linkType": "Environment"
          }
        },
        "publishedVersion": 6,
        "publishedAt": "2024-04-24T02:09:35.404Z",
        "firstPublishedAt": "2024-04-24T02:09:35.404Z",
        "createdBy": {
          "sys": {
            "type": "Link",
            "linkType": "User",
            "id": "24xELcGAn6cqGiuyQLS1MD"
          }
        },
        "updatedBy": {
          "sys": {
            "type": "Link",
            "linkType": "User",
            "id": "24xELcGAn6cqGiuyQLS1MD"
          }
        },
        "publishedCounter": 1,
        "version": 7,
        "publishedBy": {
          "sys": {
            "type": "Link",
            "linkType": "User",
            "id": "24xELcGAn6cqGiuyQLS1MD"
          }
        },
        "automationTags": [
        ],
        "contentType": {
          "sys": {
            "type": "Link",
            "linkType": "ContentType",
            "id": "hero"
          }
        },
        "urn": "crn:contentful:::content:spaces/9y6bw8wj9521/environments/master/entries/2RVp0aUqSs3oQYkM1T3Yv2"
      },
      "fields": {
        "heroTitle": {
          "en-US": "Work Experience"
        },
        "heroBody": {
          "en-US": "Lorem Ipsum is simply dummy text of the printing and typesetting industry. Lorem Ipsum has been the industry's standard dummy text ever since the 1500s, when an unknown printer took a galley of type and scrambled it to make a type specimen book. It has survived not only five centuries, but also the leap into electronic typesetting, remaining essentially unchanged. It was popularised in the 1960s with the release of Letraset sheets containing Lorem Ipsum passages, and more recently with desktop publishing software like Aldus PageMaker including versions of Lorem Ipsum."
        },
        "heroImage": {
          "en-US": {
            "sys": {
              "type": "Link",
              "linkType": "Asset",
              "id": "6PS1ewyRLpUtGDw4VB82HE"
            }
          }
        }
      }
    },
    {
      "metadata": {
        "tags": [
        ]
      },
      "sys": {
        "space": {
          "sys": {
            "type": "Link",
            "linkType": "Space",
            "id": "9y6bw8wj9521"
          }
        },
        "id": "5lR0NXKwBpIaeF1BoZ1D0y",
        "type": "Entry",
        "createdAt": "2024-04-24T02:16:20.546Z",
        "updatedAt": "2024-04-24T02:17:30.246Z",
        "environment": {
          "sys": {
            "id": "master",
            "type": "Link",
            "linkType": "Environment"
          }
        },
        "publishedVersion": 5,
        "publishedAt": "2024-04-24T02:17:30.246Z",
        "firstPublishedAt": "2024-04-24T02:17:30.246Z",
        "createdBy": {
          "sys": {
            "type": "Link",
            "linkType": "User",
            "id": "24xELcGAn6cqGiuyQLS1MD"
          }
        },
        "updatedBy": {
          "sys": {
            "type": "Link",
            "linkType": "User",
            "id": "24xELcGAn6cqGiuyQLS1MD"
          }
        },
        "publishedCounter": 1,
        "version": 6,
        "publishedBy": {
          "sys": {
            "type": "Link",
            "linkType": "User",
            "id": "24xELcGAn6cqGiuyQLS1MD"
          }
        },
        "automationTags": [
        ],
        "contentType": {
          "sys": {
            "type": "Link",
            "linkType": "ContentType",
            "id": "hero"
          }
        },
        "urn": "crn:contentful:::content:spaces/9y6bw8wj9521/environments/master/entries/5lR0NXKwBpIaeF1BoZ1D0y"
      },
      "fields": {
        "heroTitle": {
          "en-US": "Creating experiences that fuel work and life."
        },
        "heroBody": {
          "en-US": "I'm Miko, a web developer focusing mainly on frontend development, user interface and experience."
        },
        "heroImage": {
          "en-US": {
            "sys": {
              "type": "Link",
              "linkType": "Asset",
              "id": "6PS1ewyRLpUtGDw4VB82HE"
            }
          }
        }
      }
    }
  ],
  "assets": [
    {
      "metadata": {
        "tags": [
        ]
      },
      "sys": {
        "space": {
          "sys": {
            "type": "Link",
            "linkType": "Space",
            "id": "9y6bw8wj9521"
          }
        },
        "id": "18fcwON5KIn0vA8D36m85i",
        "type": "Asset",
        "createdAt": "2024-03-30T03:02:36.735Z",
        "updatedAt": "2024-04-24T02:13:22.958Z",
        "environment": {
          "sys": {
            "id": "master",
            "type": "Link",
            "linkType": "Environment"
          }
        },
        "publishedVersion": 8,
        "publishedAt": "2024-04-24T02:13:22.958Z",
        "firstPublishedAt": "2024-03-30T03:03:27.851Z",
        "createdBy": {
          "sys": {
            "type": "Link",
            "linkType": "User",
            "id": "24xELcGAn6cqGiuyQLS1MD"
          }
        },
        "updatedBy": {
          "sys": {
            "type": "Link",
            "linkType": "User",
            "id": "24xELcGAn6cqGiuyQLS1MD"
          }
        },
        "publishedCounter": 2,
        "version": 9,
        "publishedBy": {
          "sys": {
            "type": "Link",
            "linkType": "User",
            "id": "24xELcGAn6cqGiuyQLS1MD"
          }
        },
        "urn": "crn:contentful:::content:spaces/9y6bw8wj9521/environments/master/assets/18fcwON5KIn0vA8D36m85i"
      },
      "fields": {
        "title": {
          "en-US": "fujitsu"
        },
        "description": {
          "en-US": "fujitsu company logo"
        },
        "file": {
          "en-US": {
            "url": "//images.ctfassets.net/9y6bw8wj9521/18fcwON5KIn0vA8D36m85i/65ce62b9347a544ba1f4e52dcf3d1e6c/fujitsu_logo.jpg",
            "details": {
              "size": 11611,
              "image": {
                "width": 400,
                "height": 400
              }
            },
            "fileName": "fujitsu logo.jpg",
            "contentType": "image/jpeg"
          }
        }
      }
    },
    {
      "metadata": {
        "tags": [
        ]
      },
      "sys": {
        "space": {
          "sys": {
            "type": "Link",
            "linkType": "Space",
            "id": "9y6bw8wj9521"
          }
        },
        "id": "4Pl0qxQ4LYY32mhC9WH8Qr",
        "type": "Asset",
        "createdAt": "2024-03-30T03:04:13.580Z",
        "updatedAt": "2024-04-18T09:32:18.752Z",
        "environment": {
          "sys": {
            "id": "master",
            "type": "Link",
            "linkType": "Environment"
          }
        },
        "publishedVersion": 9,
        "publishedAt": "2024-04-18T09:32:18.752Z",
        "firstPublishedAt": "2024-03-30T03:04:35.750Z",
        "createdBy": {
          "sys": {
            "type": "Link",
            "linkType": "User",
            "id": "24xELcGAn6cqGiuyQLS1MD"
          }
        },
        "updatedBy": {
          "sys": {
            "type": "Link",
            "linkType": "User",
            "id": "24xELcGAn6cqGiuyQLS1MD"
          }
        },
        "publishedCounter": 3,
        "version": 10,
        "publishedBy": {
          "sys": {
            "type": "Link",
            "linkType": "User",
            "id": "24xELcGAn6cqGiuyQLS1MD"
          }
        },
        "urn": "crn:contentful:::content:spaces/9y6bw8wj9521/environments/master/assets/4Pl0qxQ4LYY32mhC9WH8Qr"
      },
      "fields": {
        "title": {
          "en-US": "workforce"
        },
        "description": {
          "en-US": "workforce company logo"
        },
        "file": {
          "en-US": {
            "url": "//images.ctfassets.net/9y6bw8wj9521/4Pl0qxQ4LYY32mhC9WH8Qr/bbb6a013c9f2fcc65259402ed1c086fa/workforce.png",
            "details": {
              "size": 10030,
              "image": {
                "width": 400,
                "height": 399
              }
            },
            "fileName": "workforce.png",
            "contentType": "image/png"
          }
        }
      }
    },
    {
      "metadata": {
        "tags": [
        ]
      },
      "sys": {
        "space": {
          "sys": {
            "type": "Link",
            "linkType": "Space",
            "id": "9y6bw8wj9521"
          }
        },
        "id": "1cQQxWEXKiPY70LSBSfkNI",
        "type": "Asset",
        "createdAt": "2024-03-30T03:05:27.739Z",
        "updatedAt": "2024-04-24T02:13:48.876Z",
        "environment": {
          "sys": {
            "id": "master",
            "type": "Link",
            "linkType": "Environment"
          }
        },
        "publishedVersion": 7,
        "publishedAt": "2024-04-24T02:13:48.876Z",
        "firstPublishedAt": "2024-03-30T03:06:06.155Z",
        "createdBy": {
          "sys": {
            "type": "Link",
            "linkType": "User",
            "id": "24xELcGAn6cqGiuyQLS1MD"
          }
        },
        "updatedBy": {
          "sys": {
            "type": "Link",
            "linkType": "User",
            "id": "24xELcGAn6cqGiuyQLS1MD"
          }
        },
        "publishedCounter": 2,
        "version": 8,
        "publishedBy": {
          "sys": {
            "type": "Link",
            "linkType": "User",
            "id": "24xELcGAn6cqGiuyQLS1MD"
          }
        },
        "urn": "crn:contentful:::content:spaces/9y6bw8wj9521/environments/master/assets/1cQQxWEXKiPY70LSBSfkNI"
      },
      "fields": {
        "title": {
          "en-US": "bolton"
        },
        "description": {
          "en-US": "bolton company logo"
        },
        "file": {
          "en-US": {
            "url": "//images.ctfassets.net/9y6bw8wj9521/1cQQxWEXKiPY70LSBSfkNI/667a7992de1c72d57d3a29e5cb4c3cdc/bolton.webp",
            "details": {
              "size": 2202,
              "image": {
                "width": 400,
                "height": 400
              }
            },
            "fileName": "bolton.webp",
            "contentType": "image/webp"
          }
        }
      }
    },
    {
      "metadata": {
        "tags": [
        ]
      },
      "sys": {
        "space": {
          "sys": {
            "type": "Link",
            "linkType": "Space",
            "id": "9y6bw8wj9521"
          }
        },
        "id": "01hO9I9HTiTMHEGjgsD17k",
        "type": "Asset",
        "createdAt": "2024-03-30T03:06:38.007Z",
        "updatedAt": "2024-04-24T02:13:36.375Z",
        "environment": {
          "sys": {
            "id": "master",
            "type": "Link",
            "linkType": "Environment"
          }
        },
        "publishedVersion": 7,
        "publishedAt": "2024-04-24T02:13:36.375Z",
        "firstPublishedAt": "2024-03-30T03:07:04.536Z",
        "createdBy": {
          "sys": {
            "type": "Link",
            "linkType": "User",
            "id": "24xELcGAn6cqGiuyQLS1MD"
          }
        },
        "updatedBy": {
          "sys": {
            "type": "Link",
            "linkType": "User",
            "id": "24xELcGAn6cqGiuyQLS1MD"
          }
        },
        "publishedCounter": 2,
        "version": 8,
        "publishedBy": {
          "sys": {
            "type": "Link",
            "linkType": "User",
            "id": "24xELcGAn6cqGiuyQLS1MD"
          }
        },
        "urn": "crn:contentful:::content:spaces/9y6bw8wj9521/environments/master/assets/01hO9I9HTiTMHEGjgsD17k"
      },
      "fields": {
        "title": {
          "en-US": "mrm"
        },
        "description": {
          "en-US": "mrm company logo"
        },
        "file": {
          "en-US": {
            "url": "//images.ctfassets.net/9y6bw8wj9521/01hO9I9HTiTMHEGjgsD17k/ac8875fe9dd36adccd2f8d86580bd4ff/mrm.png",
            "details": {
              "size": 16696,
              "image": {
                "width": 400,
                "height": 400
              }
            },
            "fileName": "mrm.png",
            "contentType": "image/png"
          }
        }
      }
    },
    {
      "metadata": {
        "tags": [
        ]
      },
      "sys": {
        "space": {
          "sys": {
            "type": "Link",
            "linkType": "Space",
            "id": "9y6bw8wj9521"
          }
        },
        "id": "6PS1ewyRLpUtGDw4VB82HE",
        "type": "Asset",
        "createdAt": "2024-04-24T02:08:01.492Z",
        "updatedAt": "2024-04-24T02:09:24.080Z",
        "environment": {
          "sys": {
            "id": "master",
            "type": "Link",
            "linkType": "Environment"
          }
        },
        "publishedVersion": 7,
        "publishedAt": "2024-04-24T02:09:24.080Z",
        "firstPublishedAt": "2024-04-24T02:09:24.080Z",
        "createdBy": {
          "sys": {
            "type": "Link",
            "linkType": "User",
            "id": "24xELcGAn6cqGiuyQLS1MD"
          }
        },
        "updatedBy": {
          "sys": {
            "type": "Link",
            "linkType": "User",
            "id": "24xELcGAn6cqGiuyQLS1MD"
          }
        },
        "publishedCounter": 1,
        "version": 8,
        "publishedBy": {
          "sys": {
            "type": "Link",
            "linkType": "User",
            "id": "24xELcGAn6cqGiuyQLS1MD"
          }
        },
        "urn": "crn:contentful:::content:spaces/9y6bw8wj9521/environments/master/assets/6PS1ewyRLpUtGDw4VB82HE"
      },
      "fields": {
        "title": {
          "en-US": "Miko Profile Image"
        },
        "description": {
          "en-US": "Miko profile image"
        },
        "file": {
          "en-US": {
            "url": "//images.ctfassets.net/9y6bw8wj9521/6PS1ewyRLpUtGDw4VB82HE/1ae8b66ed29e804f81dc618996b50e54/IMG_4480.JPG",
            "details": {
              "size": 11630600,
              "image": {
                "width": 4160,
                "height": 6240
              }
            },
            "fileName": "IMG_4480.JPG",
            "contentType": "image/jpeg"
          }
        }
      }
    }
  ],
  "locales": [
    {
      "name": "English (United States)",
      "code": "en-US",
      "fallbackCode": null,
      "default": true,
      "contentManagementApi": true,
      "contentDeliveryApi": true,
      "optional": false,
      "sys": {
        "type": "Locale",
        "id": "4eSqM484NPWLovalU3eLTP",
        "version": 1,
        "space": {
          "sys": {
            "type": "Link",
            "linkType": "Space",
            "id": "9y6bw8wj9521"
          }
        },
        "environment": {
          "sys": {
            "type": "Link",
            "linkType": "Environment",
            "id": "master",
            "uuid": "1467ccb6-8665-4ded-936c-aab3c871dfc8"
          }
        },
        "createdBy": {
          "sys": {
            "type": "Link",
            "linkType": "User",
            "id": "24xELcGAn6cqGiuyQLS1MD"
          }
        },
        "createdAt": "2024-03-20T06:18:08Z",
        "updatedBy": {
          "sys": {
            "type": "Link",
            "linkType": "User",
            "id": "24xELcGAn6cqGiuyQLS1MD"
          }
        },
        "updatedAt": "2024-03-20T06:18:08Z"
      }
    }
  ],
  "webhooks": [
    {
      "name": "Revalidate",
      "url": "https://PLACEHOLDER_DOMAIN/api/revalidation",
      "httpBasicUsername": null,
      "topics": [
        "ContentType.publish",
        "ContentType.unpublish",
        "Entry.publish",
        "Entry.unpublish",
        "Asset.publish",
        "Asset.unpublish"
      ],
      "filters": [
        {
          "equals": [
            {
              "doc": "sys.environment.sys.id"
            },
            "master"
          ]
        },
        {
          "equals": [
            {
              "doc": "sys.contentType.sys.id"
            },
            "knowledgeArticle"
          ]
        }
      ],
      "transformation": null,
      "active": true,
      "sys": {
        "type": "WebhookDefinition",
        "id": "2HJJYtunZAlclIVcuATWmn",
        "version": 0,
        "space": {
          "sys": {
            "type": "Link",
            "linkType": "Space",
            "id": "9y6bw8wj9521"
          }
        },
        "createdBy": {
          "sys": {
            "type": "Link",
            "linkType": "User",
            "id": "24xELcGAn6cqGiuyQLS1MD"
          }
        },
        "createdAt": "2024-03-20T07:21:09Z",
        "updatedBy": {
          "sys": {
            "type": "Link",
            "linkType": "User",
            "id": "24xELcGAn6cqGiuyQLS1MD"
          }
        },
        "updatedAt": "2024-03-20T07:21:09Z"
      },
      "headers": [
        {
          "key": "x-vercel-reval-key",
          "value": "ContentfulOnlySecret123"
        }
      ]
    }
  ],
  "roles": [
    {
      "name": "Author",
      "description": "Allows editing of content",
      "policies": [
        {
          "effect": "allow",
          "actions": [
            "create"
          ],
          "constraint": {
            "and": [
              {
                "equals": [
                  {
                    "doc": "sys.type"
                  },
                  "Entry"
                ]
              }
            ]
          }
        },
        {
          "effect": "allow",
          "actions": [
            "read"
          ],
          "constraint": {
            "and": [
              {
                "equals": [
                  {
                    "doc": "sys.type"
                  },
                  "Entry"
                ]
              }
            ]
          }
        },
        {
          "effect": "allow",
          "actions": [
            "update"
          ],
          "constraint": {
            "and": [
              {
                "equals": [
                  {
                    "doc": "sys.type"
                  },
                  "Entry"
                ]
              }
            ]
          }
        },
        {
          "effect": "allow",
          "actions": [
            "create"
          ],
          "constraint": {
            "and": [
              {
                "equals": [
                  {
                    "doc": "sys.type"
                  },
                  "Asset"
                ]
              }
            ]
          }
        },
        {
          "effect": "allow",
          "actions": [
            "read"
          ],
          "constraint": {
            "and": [
              {
                "equals": [
                  {
                    "doc": "sys.type"
                  },
                  "Asset"
                ]
              }
            ]
          }
        },
        {
          "effect": "allow",
          "actions": [
            "update"
          ],
          "constraint": {
            "and": [
              {
                "equals": [
                  {
                    "doc": "sys.type"
                  },
                  "Asset"
                ]
              }
            ]
          }
        }
      ],
      "permissions": {
        "ContentModel": [
          "read"
        ],
        "Settings": [
        ],
        "ContentDelivery": [
        ],
        "Environments": [
        ],
        "EnvironmentAliases": [
        ],
        "Tags": [
        ]
      },
      "sys": {
        "type": "Role",
        "id": "4feh8BeIxwynuOjtBwaixH",
        "version": 0,
        "space": {
          "sys": {
            "type": "Link",
            "linkType": "Space",
            "id": "9y6bw8wj9521"
          }
        },
        "createdBy": {
          "sys": {
            "type": "Link",
            "linkType": "User",
            "id": "24xELcGAn6cqGiuyQLS1MD"
          }
        },
        "createdAt": "2024-03-20T06:18:08Z",
        "updatedBy": {
          "sys": {
            "type": "Link",
            "linkType": "User",
            "id": "24xELcGAn6cqGiuyQLS1MD"
          }
        },
        "updatedAt": "2024-03-20T06:18:08Z"
      }
    },
    {
      "name": "Editor",
      "description": "Allows editing, publishing and archiving of content",
      "policies": [
        {
          "effect": "allow",
          "actions": "all",
          "constraint": {
            "and": [
              {
                "equals": [
                  {
                    "doc": "sys.type"
                  },
                  "Entry"
                ]
              }
            ]
          }
        },
        {
          "effect": "allow",
          "actions": "all",
          "constraint": {
            "and": [
              {
                "equals": [
                  {
                    "doc": "sys.type"
                  },
                  "Asset"
                ]
              }
            ]
          }
        }
      ],
      "permissions": {
        "ContentModel": [
          "read"
        ],
        "Settings": [
        ],
        "ContentDelivery": [
        ],
        "Environments": [
        ],
        "EnvironmentAliases": [
        ],
        "Tags": [
        ]
      },
      "sys": {
        "type": "Role",
        "id": "4feWuts86pcGEMVLayFxN7",
        "version": 0,
        "space": {
          "sys": {
            "type": "Link",
            "linkType": "Space",
            "id": "9y6bw8wj9521"
          }
        },
        "createdBy": {
          "sys": {
            "type": "Link",
            "linkType": "User",
            "id": "24xELcGAn6cqGiuyQLS1MD"
          }
        },
        "createdAt": "2024-03-20T06:18:08Z",
        "updatedBy": {
          "sys": {
            "type": "Link",
            "linkType": "User",
            "id": "24xELcGAn6cqGiuyQLS1MD"
          }
        },
        "updatedAt": "2024-03-20T06:18:08Z"
      }
    },
    {
      "name": "Translator",
      "description": "Allows editing of localized fields in the specified language",
      "policies": [
        {
          "effect": "allow",
          "actions": [
            "read"
          ],
          "constraint": {
            "and": [
              {
                "equals": [
                  {
                    "doc": "sys.type"
                  },
                  "Entry"
                ]
              }
            ]
          }
        },
        {
          "effect": "allow",
          "actions": [
            "read"
          ],
          "constraint": {
            "and": [
              {
                "equals": [
                  {
                    "doc": "sys.type"
                  },
                  "Asset"
                ]
              }
            ]
          }
        },
        {
          "effect": "allow",
          "actions": [
            "update"
          ],
          "constraint": {
            "and": [
              {
                "equals": [
                  {
                    "doc": "sys.type"
                  },
                  "Entry"
                ]
              },
              {
                "paths": [
                  {
                    "doc": "fields.%.%"
                  }
                ]
              }
            ]
          }
        },
        {
          "effect": "allow",
          "actions": [
            "update"
          ],
          "constraint": {
            "and": [
              {
                "equals": [
                  {
                    "doc": "sys.type"
                  },
                  "Asset"
                ]
              },
              {
                "paths": [
                  {
                    "doc": "fields.%.%"
                  }
                ]
              }
            ]
          }
        }
      ],
      "permissions": {
        "ContentModel": [
          "read"
        ],
        "Settings": [
        ],
        "ContentDelivery": [
        ],
        "Environments": [
        ],
        "EnvironmentAliases": [
        ],
        "Tags": [
        ]
      },
      "sys": {
        "type": "Role",
        "id": "4ffr50hcJXAOWjpk5ul8Fr",
        "version": 0,
        "space": {
          "sys": {
            "type": "Link",
            "linkType": "Space",
            "id": "9y6bw8wj9521"
          }
        },
        "createdBy": {
          "sys": {
            "type": "Link",
            "linkType": "User",
            "id": "24xELcGAn6cqGiuyQLS1MD"
          }
        },
        "createdAt": "2024-03-20T06:18:08Z",
        "updatedBy": {
          "sys": {
            "type": "Link",
            "linkType": "User",
            "id": "24xELcGAn6cqGiuyQLS1MD"
          }
        },
        "updatedAt": "2024-03-20T06:18:08Z"
      }
    }
  ]
}